MIMIC3py/ICD9_One_Hot_Encoded.py
MIMIC3py/__init__.py
MIMIC3py/config.py
MIMIC3py/download.py
MIMIC3py/load_to_pandas.py
MIMIC3py/sandbox.py
MIMIC3py/utilities.py
MIMIC3py-0.11.dist-info/DESCRIPTION.rst
MIMIC3py-0.11.dist-info/METADATA
MIMIC3py-0.11.dist-info/RECORD
MIMIC3py-0.11.dist-info/WHEEL
MIMIC3py-0.11.dist-info/metadata.json
MIMIC3py-0.11.dist-info/top_level.txt
