Metadata-Version: 2.0
Name: MIMIC3py
Version: 0.11
Summary: A Python library to load and analyze the MIMIC III Critical Care Database.
Home-page: https://github.com/SpiroGanas/MIMIC3py
Author: Spiro Ganas
Author-email: spiroganas@gatech.edu
License: UNKNOWN
Download-URL: https://github.com/SpiroGanas/MIMIC3py/archive/v0.11.tar.gz
Keywords: MIMIC,Critical Care,Informatics
Platform: UNKNOWN
Classifier: Development Status :: 2 - Pre-Alpha
Classifier: License :: OSI Approved :: MIT License
Classifier: Programming Language :: Python :: 3
Classifier: Intended Audience :: Healthcare Industry
Classifier: Intended Audience :: Science/Research
Requires-Python: >=3
Requires-Dist: pandas
Requires-Dist: numpy
Requires-Dist: scikit-learn
Requires-Dist: requests
